nucosMQ
